source_close_com/__init__.py
source_close_com/datetime_incremental_sync.py
source_close_com/manifest.yaml
source_close_com/run.py
source_close_com/schemas/activity_custom_fields.json
source_close_com/schemas/answered_detached_call_tasks.json
source_close_com/schemas/call_activities.json
source_close_com/schemas/contact_custom_fields.json
source_close_com/schemas/contacts.json
source_close_com/schemas/created_activities.json
source_close_com/schemas/custom_activities.json
source_close_com/schemas/custom_email_connected_accounts.json
source_close_com/schemas/delete_bulk_actions.json
source_close_com/schemas/dialer.json
source_close_com/schemas/edit_bulk_actions.json
source_close_com/schemas/email_activities.json
source_close_com/schemas/email_bulk_actions.json
source_close_com/schemas/email_followup_tasks.json
source_close_com/schemas/email_sequences.json
source_close_com/schemas/email_templates.json
source_close_com/schemas/email_thread_activities.json
source_close_com/schemas/events.json
source_close_com/schemas/google_connected_accounts.json
source_close_com/schemas/incoming_email_tasks.json
source_close_com/schemas/incoming_sms_tasks.json
source_close_com/schemas/integration_links.json
source_close_com/schemas/lead_custom_fields.json
source_close_com/schemas/lead_status_change_activities.json
source_close_com/schemas/lead_statuses.json
source_close_com/schemas/lead_tasks.json
source_close_com/schemas/leads.json
source_close_com/schemas/meeting_activities.json
source_close_com/schemas/missed_call_tasks.json
source_close_com/schemas/note_activities.json
source_close_com/schemas/opportunities.json
source_close_com/schemas/opportunity_custom_fields.json
source_close_com/schemas/opportunity_due_tasks.json
source_close_com/schemas/opportunity_status_change_activities.json
source_close_com/schemas/opportunity_statuses.json
source_close_com/schemas/pipelines.json
source_close_com/schemas/roles.json
source_close_com/schemas/send_as.json
airbyte_source_close_com-0.5.30.dist-info/METADATA
airbyte_source_close_com-0.5.30.dist-info/WHEEL
airbyte_source_close_com-0.5.30.dist-info/entry_points.txt
airbyte_source_close_com-0.5.30.dist-info/RECORD
