Metadata-Version: 2.3
Name: airbyte-source-close-com
Version: 0.5.30
Summary: Source implementation for Close.com.
Home-page: https://airbyte.com
License: MIT
Author: Airbyte
Author-email: contact@airbyte.io
Requires-Python: >=3.9,<3.12
Classifier: License :: OSI Approved :: MIT License
Classifier: Programming Language :: Python :: 3
Classifier: Programming Language :: Python :: 3.9
Classifier: Programming Language :: Python :: 3.10
Classifier: Programming Language :: Python :: 3.11
Requires-Dist: airbyte-cdk (>=0,<1)
Requires-Dist: pendulum (==2.1.2)
Requires-Dist: requests (==2.31.0)
Project-URL: Documentation, https://docs.airbyte.com/integrations/sources/close-com
Project-URL: Repository, https://github.com/airbytehq/airbyte
